easy_http/__init__.py
easy_http/server.py
ezhttpy-0.1.1.dist-info/licenses/LICENSE
ezhttpy-0.1.1.dist-info/METADATA
ezhttpy-0.1.1.dist-info/WHEEL
ezhttpy-0.1.1.dist-info/top_level.txt
ezhttpy-0.1.1.dist-info/RECORD
