Metadata-Version: 2.4
Name: ezhttpy
Version: 0.1.1
Summary: Simple HTTP server with custom commands and HTML support
Home-page: https://easy_http.denisvarga.eu/
Author: Denis Varga
Author-email: mail@denisvarga.eu
Classifier: Programming Language :: Python :: 3
Classifier: License :: OSI Approved :: MIT License
Classifier: Operating System :: OS Independent
Requires-Python: >=3.7
License-File: LICENSE
Dynamic: author
Dynamic: author-email
Dynamic: classifier
Dynamic: description
Dynamic: description-content-type
Dynamic: home-page
Dynamic: license-file
Dynamic: requires-python
Dynamic: summary
